<?xml version="1.0" encoding="ISO-8859-1"?>
<resources>
    <entities>
        <entity id="common-resource" reference="resource:erland/webapp/common/resource.xml"/>
        <entity id="common-metadatafielddescription" reference="descriptiontag:erland/webapp/common/descriptiontag.xml"/>
        <entity id="usermgmt-user" reference="user:erland/webapp/usermgmt/user.xml"/>
        <entity id="usermgmt-userapplicationrole" reference="userapplicationrole:erland/webapp/usermgmt/userapplicationrole.xml"/>
        <entity id="usermgmt-userinfo" reference="userinfo:erland/webapp/usermgmt/userinfo.xml"/>
        <entity id="homepage-useraccount" reference="useraccount:erland/webapp/homepage/entity/account/useraccount.xml"/>
        <entity id="homepage-section" reference="section:erland/webapp/homepage/entity/section/section.xml"/>
        <entity id="homepage-service" reference="service:erland/webapp/homepage/entity/service/service.xml"/>
    </entities>
</resources>